logpoint/__init__.py
logpoint/logpoint.py
logpoint-0.0.2.dist-info/METADATA
logpoint-0.0.2.dist-info/WHEEL
logpoint-0.0.2.dist-info/top_level.txt
logpoint-0.0.2.dist-info/RECORD
