Metadata-Version: 2.1
Name: logpoint
Version: 0.0.2
Summary: implements logpoint api
Home-page: https://github.com/shubhajeet/logpointapi
Author: Sujit Maharjan
Author-email: shubhajeet.per@gmail.com
License: UNKNOWN
Platform: UNKNOWN
Classifier: Programming Language :: Python :: 3
Classifier: Operating System :: OS Independent
Requires-Python: >=3.6
